odoo10_addon_account_due_list_payment_mode-10.0.1.0.0-py2.7-nspkg.pth
odoo/addons/account_due_list_payment_mode/README.rst
odoo/addons/account_due_list_payment_mode/__init__.py
odoo/addons/account_due_list_payment_mode/__manifest__.py
odoo/addons/account_due_list_payment_mode/i18n/es.po
odoo/addons/account_due_list_payment_mode/models/__init__.py
odoo/addons/account_due_list_payment_mode/models/account_move_line.py
odoo/addons/account_due_list_payment_mode/views/payment_view.xml
odoo10_addon_account_due_list_payment_mode-10.0.1.0.0.dist-info/DESCRIPTION.rst
odoo10_addon_account_due_list_payment_mode-10.0.1.0.0.dist-info/METADATA
odoo10_addon_account_due_list_payment_mode-10.0.1.0.0.dist-info/RECORD
odoo10_addon_account_due_list_payment_mode-10.0.1.0.0.dist-info/WHEEL
odoo10_addon_account_due_list_payment_mode-10.0.1.0.0.dist-info/metadata.json
odoo10_addon_account_due_list_payment_mode-10.0.1.0.0.dist-info/namespace_packages.txt
odoo10_addon_account_due_list_payment_mode-10.0.1.0.0.dist-info/top_level.txt
