Metadata-Version: 2.0
Name: odoo10-addon-account-due-list-payment-mode
Version: 10.0.1.0.0
Summary: Payment due list with payment mode
Home-page: https://odoo-community.org/
Author: Obertix Free Solutions, Tecnativa, Odoo Community Association (OCA),
Author-email: support@odoo-community.org
License: UNKNOWN
Platform: UNKNOWN
Classifier: Programming Language :: Python :: 2.7
Classifier: Framework :: Odoo
Requires-Dist: odoo (<10.1dev,>=10.0)
Requires-Dist: odoo10-addon-account-due-list
Requires-Dist: odoo10-addon-account-payment-partner
